ccnuacm_datamocker/__init__.py
ccnuacm_datamocker-0.0.6.dist-info/LICENSE
ccnuacm_datamocker-0.0.6.dist-info/METADATA
ccnuacm_datamocker-0.0.6.dist-info/WHEEL
ccnuacm_datamocker-0.0.6.dist-info/top_level.txt
ccnuacm_datamocker-0.0.6.dist-info/RECORD
