Metadata-Version: 2.1
Name: ccnuacm_datamocker
Version: 0.0.6
Summary: A data mocking library for CCNU ACM
Home-page: https://github.com/CCNU-ACM-Official/CCNUACM_DataMocker.git
Author: JixiangXiong
Author-email: xiongjx751@qq.com
Classifier: License :: OSI Approved :: MIT License
Classifier: Programming Language :: Python
Classifier: Programming Language :: Python :: 3
Classifier: Programming Language :: Python :: 3.10
License-File: LICENSE
Requires-Dist: numpy
Requires-Dist: jupyter
Requires-Dist: tqdm
